[{"name": "auto_features", "value": "auto", "section": "core", "machine": "any", "choices": ["enabled", "disabled", "auto"], "type": "combo", "description": "Override value of all 'auto' features"}, {"name": "backend", "value": "ninja", "section": "core", "machine": "any", "choices": ["ninja", "vs", "vs2010", "vs2015", "vs2017", "vs2019", "xcode"], "type": "combo", "description": "Backend to use"}, {"name": "buildtype", "value": "debugoptimized", "section": "core", "machine": "any", "choices": ["plain", "debug", "debugoptimized", "release", "minsize", "custom"], "type": "combo", "description": "Build type to use"}, {"name": "debug", "value": true, "section": "core", "machine": "any", "type": "boolean", "description": "Debug"}, {"name": "default_library", "value": "shared", "section": "core", "machine": "any", "choices": ["shared", "static", "both"], "type": "combo", "description": "Default library type"}, {"name": "install_umask", "value": 18, "section": "core", "machine": "any", "type": "integer", "description": "Default umask to apply on permissions of installed files"}, {"name": "layout", "value": "mirror", "section": "core", "machine": "any", "choices": ["mirror", "flat"], "type": "combo", "description": "Build directory layout"}, {"name": "optimization", "value": "2", "section": "core", "machine": "any", "choices": ["0", "g", "1", "2", "3", "s"], "type": "combo", "description": "Optimization level"}, {"name": "strip", "value": false, "section": "core", "machine": "any", "type": "boolean", "description": "Strip targets on install"}, {"name": "unity", "value": "off", "section": "core", "machine": "any", "choices": ["on", "off", "subprojects"], "type": "combo", "description": "Unity build"}, {"name": "warning_level", "value": "2", "section": "core", "machine": "any", "choices": ["0", "1", "2", "3"], "type": "combo", "description": "Compiler warning level to use"}, {"name": "werror", "value": false, "section": "core", "machine": "any", "type": "boolean", "description": "Treat warnings as errors"}, {"name": "wrap_mode", "value": "default", "section": "core", "machine": "any", "choices": ["default", "nofallback", "nodownload", "forcefallback"], "type": "combo", "description": "Wrap mode"}, {"name": "cmake_prefix_path", "value": [], "section": "core", "machine": "host", "type": "array", "description": "List of additional prefixes for cmake to search"}, {"name": "pkg_config_path", "value": ["/opt/vc/lib/pkgconfig", "/usr/lib/arm-linux-gnueabihf/pkgconfig", "/usr/lib/pkgconfig", "/usr/local/lib/arm-linux-gnueabihf/pkgconfig", "/usr/share/pkgconfig", "/usr/local/lib/pkgconfig", "/home/pi/spice/usr/lib/pkgconfig", "/home/pi/spice/usr/share/pkgconfig", "/home/pi/spice/usr/lib/arm-linux-gnueabihf/pkgconfig"], "section": "core", "machine": "host", "type": "array", "description": "List of additional paths for pkg-config to search"}, {"name": "build.cmake_prefix_path", "value": [], "section": "core", "machine": "build", "type": "array", "description": "List of additional prefixes for cmake to search"}, {"name": "build.pkg_config_path", "value": ["/opt/vc/lib/pkgconfig", "/usr/lib/arm-linux-gnueabihf/pkgconfig", "/usr/lib/pkgconfig", "/usr/local/lib/arm-linux-gnueabihf/pkgconfig", "/usr/share/pkgconfig", "/usr/local/lib/pkgconfig", "/home/pi/spice/usr/lib/pkgconfig", "/home/pi/spice/usr/share/pkgconfig", "/home/pi/spice/usr/lib/arm-linux-gnueabihf/pkgconfig"], "section": "core", "machine": "build", "type": "array", "description": "List of additional paths for pkg-config to search"}, {"name": "backend_max_links", "value": 0, "section": "backend", "machine": "any", "type": "integer", "description": "Maximum number of linker processes to run or 0 for no limit"}, {"name": "b_asneeded", "value": true, "section": "base", "machine": "any", "type": "boolean", "description": "Use -Wl,--as-needed when linking"}, {"name": "b_colorout", "value": "always", "section": "base", "machine": "any", "choices": ["auto", "always", "never"], "type": "combo", "description": "Use colored output"}, {"name": "b_coverage", "value": false, "section": "base", "machine": "any", "type": "boolean", "description": "Enable coverage tracking."}, {"name": "b_lto", "value": false, "section": "base", "machine": "any", "type": "boolean", "description": "Use link time optimization"}, {"name": "b_lundef", "value": true, "section": "base", "machine": "any", "type": "boolean", "description": "Use -Wl,--no-undefined when linking"}, {"name": "b_ndebug", "value": "false", "section": "base", "machine": "any", "choices": ["true", "false", "if-release"], "type": "combo", "description": "Disable asserts"}, {"name": "b_pch", "value": true, "section": "base", "machine": "any", "type": "boolean", "description": "Use precompiled headers"}, {"name": "b_pgo", "value": "off", "section": "base", "machine": "any", "choices": ["off", "generate", "use"], "type": "combo", "description": "Use profile guided optimization"}, {"name": "b_pie", "value": false, "section": "base", "machine": "any", "type": "boolean", "description": "Build executables as position independent"}, {"name": "b_sanitize", "value": "none", "section": "base", "machine": "any", "choices": ["none", "address", "thread", "undefined", "memory", "address,undefined"], "type": "combo", "description": "Code sanitizer to use"}, {"name": "b_staticpic", "value": true, "section": "base", "machine": "any", "type": "boolean", "description": "Build static libraries as position independent"}, {"name": "c_args", "value": [], "section": "compiler", "machine": "host", "type": "array", "description": "Extra arguments passed to the C compiler"}, {"name": "c_link_args", "value": [], "section": "compiler", "machine": "host", "type": "array", "description": "Extra arguments passed to the C linker"}, {"name": "c_std", "value": "none", "section": "compiler", "machine": "host", "choices": ["none", "c89", "c99", "c11", "c17", "c18", "gnu89", "gnu99", "gnu11", "gnu17", "gnu18"], "type": "combo", "description": "C language standard to use"}, {"name": "build.c_args", "value": [], "section": "compiler", "machine": "build", "type": "array", "description": "Extra arguments passed to the C compiler"}, {"name": "build.c_link_args", "value": [], "section": "compiler", "machine": "build", "type": "array", "description": "Extra arguments passed to the C linker"}, {"name": "build.c_std", "value": "none", "section": "compiler", "machine": "build", "choices": ["none", "c89", "c99", "c11", "c17", "c18", "gnu89", "gnu99", "gnu11", "gnu17", "gnu18"], "type": "combo", "description": "C language standard to use"}, {"name": "bindir", "value": "bin", "section": "directory", "machine": "any", "type": "string", "description": "Executable directory"}, {"name": "datadir", "value": "share", "section": "directory", "machine": "any", "type": "string", "description": "Data file directory"}, {"name": "includedir", "value": "include", "section": "directory", "machine": "any", "type": "string", "description": "Header file directory"}, {"name": "infodir", "value": "share/info", "section": "directory", "machine": "any", "type": "string", "description": "Info page directory"}, {"name": "libdir", "value": "lib/arm-linux-gnueabihf", "section": "directory", "machine": "any", "type": "string", "description": "Library directory"}, {"name": "libexecdir", "value": "libexec", "section": "directory", "machine": "any", "type": "string", "description": "Library executable directory"}, {"name": "localedir", "value": "share/locale", "section": "directory", "machine": "any", "type": "string", "description": "Locale data directory"}, {"name": "localstatedir", "value": "var", "section": "directory", "machine": "any", "type": "string", "description": "Localstate data directory"}, {"name": "mandir", "value": "share/man", "section": "directory", "machine": "any", "type": "string", "description": "Manual page directory"}, {"name": "prefix", "value": "/home/pi/spice/usr", "section": "directory", "machine": "any", "type": "string", "description": "Installation prefix"}, {"name": "sbindir", "value": "sbin", "section": "directory", "machine": "any", "type": "string", "description": "System executable directory"}, {"name": "sharedstatedir", "value": "com", "section": "directory", "machine": "any", "type": "string", "description": "Architecture-independent data directory"}, {"name": "sysconfdir", "value": "etc", "section": "directory", "machine": "any", "type": "string", "description": "Sysconf data directory"}, {"name": "alignment-checks", "value": false, "section": "user", "machine": "any", "type": "boolean", "description": "Enable runtime checks for cast alignment"}, {"name": "builtin-mjpeg", "value": true, "section": "user", "machine": "any", "type": "boolean", "description": "Enable the builtin mjpeg video decoder"}, {"name": "celt051", "value": "auto", "section": "user", "machine": "any", "choices": ["enabled", "disabled", "auto"], "type": "combo", "description": "Enable celt051 audio codec"}, {"name": "coroutine", "value": "auto", "section": "user", "machine": "any", "choices": ["auto", "ucontext", "gthread", "winfiber"], "type": "combo", "description": "Use ucontext or GThread for coroutines"}, {"name": "gtk", "value": "auto", "section": "user", "machine": "any", "choices": ["enabled", "disabled", "auto"], "type": "combo", "description": "Enable gtk+"}, {"name": "gtk_doc", "value": "auto", "section": "user", "machine": "any", "choices": ["enabled", "disabled", "auto"], "type": "combo", "description": "Generate API documentation with gtk-doc"}, {"name": "introspection", "value": "auto", "section": "user", "machine": "any", "choices": ["enabled", "disabled", "auto"], "type": "combo", "description": "Check for GObject instrospection requirements"}, {"name": "lz4", "value": "auto", "section": "user", "machine": "any", "choices": ["enabled", "disabled", "auto"], "type": "combo", "description": "Enable lz4 compression support"}, {"name": "opus", "value": "auto", "section": "user", "machine": "any", "choices": ["enabled", "disabled", "auto"], "type": "combo", "description": "Enable Opus audio codec"}, {"name": "pie", "value": true, "section": "user", "machine": "any", "type": "boolean", "description": "Enable position-independent-executable support for the USB acl helper"}, {"name": "polkit", "value": "auto", "section": "user", "machine": "any", "choices": ["enabled", "disabled", "auto"], "type": "combo", "description": "Enable PolicyKit support for the USB acl helper"}, {"name": "pulse", "value": "auto", "section": "user", "machine": "any", "choices": ["enabled", "disabled", "auto"], "type": "combo", "description": "Enable the PulseAudio backend"}, {"name": "recorder", "value": false, "section": "user", "machine": "any", "type": "boolean", "description": "Enable recorder instrumentation"}, {"name": "sasl", "value": "auto", "section": "user", "machine": "any", "choices": ["enabled", "disabled", "auto"], "type": "combo", "description": "Use cyrus SASL authentication"}, {"name": "smartcard", "value": "auto", "section": "user", "machine": "any", "choices": ["enabled", "disabled", "auto"], "type": "combo", "description": "Enable smartcard support"}, {"name": "spice-common:alignment-checks", "value": false, "section": "user", "machine": "any", "type": "boolean", "description": "Enable runtime checks for cast alignment"}, {"name": "spice-common:celt051", "value": "disabled", "section": "user", "machine": "any", "choices": ["enabled", "disabled", "auto"], "type": "combo", "description": "Enable celt051 audio codec"}, {"name": "spice-common:extra-checks", "value": false, "section": "user", "machine": "any", "type": "boolean", "description": "Enable extra checks on code"}, {"name": "spice-common:generate-code", "value": "client", "section": "user", "machine": "any", "choices": ["all", "server", "client"], "type": "combo", "description": "Which code should be built"}, {"name": "spice-common:instrumentation", "value": "no", "section": "user", "machine": "any", "choices": ["recorder", "agent", "no"], "type": "combo", "description": "Enable instrumentation"}, {"name": "spice-common:manual", "value": true, "section": "user", "machine": "any", "type": "boolean", "description": "Build SPICE manual"}, {"name": "spice-common:opus", "value": "auto", "section": "user", "machine": "any", "choices": ["enabled", "disabled", "auto"], "type": "combo", "description": "Enable Opus audio codec"}, {"name": "spice-common:python-checks", "value": true, "section": "user", "machine": "any", "type": "boolean", "description": "Enable checks for Python modules needed to build from git"}, {"name": "spice-common:smartcard", "value": "auto", "section": "user", "machine": "any", "choices": ["enabled", "disabled", "auto"], "type": "combo", "description": "Enable smartcard support"}, {"name": "spice-common:tests", "value": true, "section": "user", "machine": "any", "type": "boolean", "description": "Enable SPICE tests"}, {"name": "usb-acl-helper-dir", "value": "", "section": "user", "machine": "any", "type": "string", "description": "Directory where the USB ACL helper binary should be installed"}, {"name": "usb-ids-path", "value": "", "section": "user", "machine": "any", "type": "string", "description": "Specify the path to usb.ids"}, {"name": "usbredir", "value": "auto", "section": "user", "machine": "any", "choices": ["enabled", "disabled", "auto"], "type": "combo", "description": "Enable usbredir support"}, {"name": "vapi", "value": "auto", "section": "user", "machine": "any", "choices": ["enabled", "disabled", "auto"], "type": "combo", "description": "Check for vala requirements"}, {"name": "webdav", "value": "auto", "section": "user", "machine": "any", "choices": ["enabled", "disabled", "auto"], "type": "combo", "description": "Enable webdav support"}, {"name": "errorlogs", "value": true, "section": "test", "machine": "any", "type": "boolean", "description": "Whether to print the logs from failing tests"}, {"name": "stdsplit", "value": true, "section": "test", "machine": "any", "type": "boolean", "description": "Split stdout and stderr in test logs"}]